{
  "endpoint": "shop",
  "schema": {
    "apiFields": [
      {
        "fieldId": "name",
        "name": "店名",
        "kind": "text",
        "required": true
      },
      {
        "fieldId": "address",
        "name": "住所",
        "kind": "text",
        "required": true
      },
      {
        "fieldId": "latitude",
        "name": "緯度",
        "kind": "number",
        "required": true
      },
      {
        "fieldId": "longitude",
        "name": "経度",
        "kind": "number",
        "required": true
      },
      {
        "fieldId": "area",
        "name": "エリア",
        "kind": "relation",
        "required": true,
        "referencedApiEndpoint": "area"
      },
      {
        "fieldId": "genre",
        "name": "ジャンル",
        "kind": "relation",
        "required": true,
        "referencedApiEndpoint": "genre"
      },
      {
        "fieldId": "memo",
        "name": "メモ",
        "kind": "textArea",
        "required": true
      },
      {
        "fieldId": "is_recommended",
        "name": "おすすめフラグ",
        "kind": "boolean",
        "required": true
      },
      {
        "fieldId": "rating",
        "name": "評価",
        "kind": "number",
        "required": false
      },
      {
        "fieldId": "nearest_station",
        "name": "最寄駅",
        "kind": "text",
        "required": false
      }
    ],
    "customFields": []
  }
}
